{
  "general:einsatzid": "1546",
  "general:title": "Dachstuhlbrand",
  "general:date": "2008-07-24T19:11:00+02:00",
  "general:location": "Zweibrückerstraße",
  "general:categorie": "Brandeinsatz",
  "general:length": "3.0",
  "general:dateFormatted": "24.07.2008 19:11",
  "general:mediaAvailable": "true",
  "general:virtualEinsatzId": "215",
  "picture:Picture": {
    "picture:PicturePreviewURL": "https://www.feuerwehr-landau.de/einsatz/einsatzbilder/vorschaubilder/0807/080724_01.jpg",
    "picture:PictureUrl": "https://www.feuerwehr-landau.de/einsatz/einsatzbilder/vollbilder/0807/080724_01.jpg",
    "picture:PictureFormat": "quer",
    "picture:PictureDescription": "",
    "picture:BufferPreview": "true",
    "picture:BufferPicture": "false"
  },
  "general:changed_on": "2017-01-02T18:35:35+01:00",
  "general:AmountPA": "8",
  "general:AmountPeople": "37",
  "general:EinsatzDescription": "Dachstuhlbrand in Mehrfamilienhaus. Beim Eintreffen der Feuerwehr war der komplette Dachstuhl aufgehitzt verbunden mit einer starken Rauchentwicklung. Mit zwei Innenangriffen und ?ber den Korb des Teleskopgelenkmastes wurde das Feuer bek?mpft. Die Einsatzkr?fte deckten den Dachstuhl ab um alle Brandnester abzul?schen. <br><br>Aus dem Internetangebot von <a href=\"http://www.swr.de\">www.swr.de</a>:<br><br>Ursache f?r Speicherbrand gekl?rt\r\n<br><br>\r\nDie Ursache f?r den Brand in einem Speicher gestern Nachmittag ist gekl?rt. Eine Gl?hbirne habe das Feuer ausgel?st, das f?r einen Schaden von 100.000 Euro sorgte, teilte die Polizei heute mit. Das h?tten die Ermittlungen des Brandsachverst?ndigen und der Kriminalpolizei ergeben. Der Dachstuhl des Hauses war v?llig ausgebrannt. Die Feuerwehr war mit 33 Mann im Einsatz gewesen. Verletzt wurde aber niemand.",
  "general:visits": "3635",
  "general:vehicles": {
    "general:vehicle": [
      {
        "general:vehicleid": "1",
        "general:vehicleVersion": "0",
        "general:vehicleName": "ELW 1",
        "picture:Picture": {
          "picture:PicturePreviewURL": "https://www.feuerwehr-landau.de/technik/fahrzeugbilder/vorschaubilder/LD-207.jpg",
          "picture:PictureUrl": "https://www.feuerwehr-landau.de/technik/fahrzeugbilder/vollbilder/LD-207.jpg",
          "picture:PictureFormat": "quer",
          "picture:PictureDescription": "",
          "picture:BufferPreview": "true",
          "picture:BufferPicture": "true"
        },
        "general:vehicleDescription": "Einsatzleitwagen",
        "general:vehicleChassis": "VW LT",
        "general:vehicleBuild": "<a href=\"http://www.hensel-fahrzeugbau.de\" target=\"new\">Hensel</a>",
        "general:vehicleMobilization": "12/04"
      },
      {
        "general:vehicleid": "45",
        "general:vehicleVersion": "0",
        "general:vehicleName": "KdoW",
        "picture:Picture": {
          "picture:PicturePreviewURL": "https://www.feuerwehr-landau.de/technik/fahrzeugbilder/vorschaubilder/LD-299.jpg",
          "picture:PictureUrl": "https://www.feuerwehr-landau.de/technik/fahrzeugbilder/vollbilder/LD-299.jpg",
          "picture:PictureFormat": "quer",
          "picture:PictureDescription": "",
          "picture:BufferPreview": "true",
          "picture:BufferPicture": "true"
        },
        "general:vehicleDescription": "Kommandowagen",
        "general:vehicleChassis": "VW Passat",
        "general:vehicleBuild": "VW",
        "general:vehicleMobilization": "03/05"
      },
      {
        "general:vehicleid": "53",
        "general:vehicleVersion": "0",
        "general:vehicleName": "KdoW 2",
        "picture:Picture": {
          "picture:PicturePreviewURL": "https://www.feuerwehr-landau.de/technik/fahrzeugbilder/vorschaubilder/LD1501.jpg",
          "picture:PictureUrl": "https://www.feuerwehr-landau.de/technik/fahrzeugbilder/vollbilder/LD1501.jpg",
          "picture:PictureFormat": "quer",
          "picture:PictureDescription": "",
          "picture:BufferPreview": "true",
          "picture:BufferPicture": "true"
        },
        "general:vehicleDescription": "Kommandowagen - Fahrzeug für den feuerwehrtechnischen Bediensteten",
        "general:vehicleChassis": "Fiat Grande Punto",
        "general:vehicleBuild": "Michael Schmidt mobile Kommunikation GmbH",
        "general:vehicleMobilization": "12/07"
      },
      {
        "general:vehicleid": "2",
        "general:vehicleVersion": "0",
        "general:vehicleName": "LF 16-12-1 (heute: HLF 20/16-2)",
        "picture:Picture": {
          "picture:PicturePreviewURL": "https://www.feuerwehr-landau.de/technik/fahrzeugbilder/vorschaubilder/LD-204.jpg",
          "picture:PictureUrl": "https://www.feuerwehr-landau.de/technik/fahrzeugbilder/vollbilder/LD-204.jpg",
          "picture:PictureFormat": "quer",
          "picture:PictureDescription": "",
          "picture:BufferPreview": "true",
          "picture:BufferPicture": "true"
        },
        "general:vehicleDescription": "Löschgruppenfahrzeug",
        "general:vehicleChassis": "IVECO 135E24W",
        "general:vehicleBuild": "<a href=\"http://www.iveco-magirus.de/\" target=\"new\">Iveco-Magirus</a>",
        "general:vehicleMobilization": "03/02"
      },
      {
        "general:vehicleid": "3",
        "general:vehicleVersion": "0",
        "general:vehicleName": "TLF 16-25",
        "picture:Picture": {
          "picture:PicturePreviewURL": "https://www.feuerwehr-landau.de/technik/fahrzeugbilder/vorschaubilder/LD-312.JPG",
          "picture:PictureUrl": "https://www.feuerwehr-landau.de/technik/fahrzeugbilder/vollbilder/LD-312.JPG",
          "picture:PictureFormat": "quer",
          "picture:PictureDescription": "",
          "picture:BufferPreview": "true",
          "picture:BufferPicture": "true"
        },
        "general:vehicleDescription": "Tanklöschfahrzeug",
        "general:vehicleChassis": "MB 1222",
        "general:vehicleBuild": "<a href=\"http://www.ziegler.de/index_de.php\" target=\"new\">Ziegler</a>",
        "general:vehicleMobilization": "02/86"
      },
      {
        "general:vehicleid": "4",
        "general:vehicleVersion": "0",
        "general:vehicleName": "TGM 23-12",
        "picture:Picture": {
          "picture:PicturePreviewURL": "https://www.feuerwehr-landau.de/technik/fahrzeugbilder/vorschaubilder/LD-243.JPG",
          "picture:PictureUrl": "https://www.feuerwehr-landau.de/technik/fahrzeugbilder/vollbilder/LD-243.JPG",
          "picture:PictureFormat": "quer",
          "picture:PictureDescription": "",
          "picture:BufferPreview": "true",
          "picture:BufferPicture": "true"
        },
        "general:vehicleDescription": "Teleskopgelenkmast",
        "general:vehicleChassis": "MAN 15.264",
        "general:vehicleBuild": "<a href=\"http://www.bronto.ch/\" target=\"new\">Bronto Skylift</a>",
        "general:vehicleMobilization": "11/98"
      },
      {
        "general:vehicleid": "5",
        "general:vehicleVersion": "0",
        "general:vehicleName": "LF 16-12-2 (heute: )",
        "picture:Picture": {
          "picture:PicturePreviewURL": "https://www.feuerwehr-landau.de/technik/fahrzeugbilder/vorschaubilder/LD-256.jpg",
          "picture:PictureUrl": "https://www.feuerwehr-landau.de/technik/fahrzeugbilder/vollbilder/LD-256.jpg",
          "picture:PictureFormat": "quer",
          "picture:PictureDescription": "",
          "picture:BufferPreview": "true",
          "picture:BufferPicture": "true"
        },
        "general:vehicleDescription": "Löschgruppenfahrzeug",
        "general:vehicleChassis": "MB 1222",
        "general:vehicleBuild": "<a href=\"http://www.ziegler.de/index_de.php\" target=\"new\">Ziegler</a>",
        "general:vehicleMobilization": "06/88"
      },
      {
        "general:vehicleid": "11",
        "general:vehicleVersion": "0",
        "general:vehicleName": "MTF 2",
        "picture:Picture": {
          "picture:PicturePreviewURL": "https://www.feuerwehr-landau.de/technik/fahrzeugbilder/vorschaubilder/LD-220.jpg",
          "picture:PictureUrl": "https://www.feuerwehr-landau.de/technik/fahrzeugbilder/vollbilder/LD-220.jpg",
          "picture:PictureFormat": "quer",
          "picture:PictureDescription": "",
          "picture:BufferPreview": "true",
          "picture:BufferPicture": "true"
        },
        "general:vehicleDescription": "Mannschaftstransportfahrzeug",
        "general:vehicleChassis": "VW LT",
        "general:vehicleBuild": "Massong",
        "general:vehicleMobilization": "12/04"
      }
    ]
  },
  "picture:Pictures": {
    "picture:Picture": [
      {
        "picture:PicturePreviewURL": "https://www.feuerwehr-landau.de/einsatz/einsatzbilder/vorschaubilder/0807/080724_01.jpg",
        "picture:PictureUrl": "https://www.feuerwehr-landau.de/einsatz/einsatzbilder/vollbilder/0807/080724_01.jpg",
        "picture:PictureFormat": "quer",
        "picture:PictureDescription": "",
        "picture:BufferPreview": "true",
        "picture:BufferPicture": "false"
      },
      {
        "picture:PicturePreviewURL": "https://www.feuerwehr-landau.de/einsatz/einsatzbilder/vorschaubilder/0807/080724_03.jpg",
        "picture:PictureUrl": "https://www.feuerwehr-landau.de/einsatz/einsatzbilder/vollbilder/0807/080724_03.jpg",
        "picture:PictureFormat": "quer",
        "picture:PictureDescription": "",
        "picture:BufferPreview": "true",
        "picture:BufferPicture": "false"
      },
      {
        "picture:PicturePreviewURL": "https://www.feuerwehr-landau.de/einsatz/einsatzbilder/vorschaubilder/0807/080724_07.jpg",
        "picture:PictureUrl": "https://www.feuerwehr-landau.de/einsatz/einsatzbilder/vollbilder/0807/080724_07.jpg",
        "picture:PictureFormat": "quer",
        "picture:PictureDescription": "",
        "picture:BufferPreview": "true",
        "picture:BufferPicture": "false"
      }
    ]
  },
  "general:OtherHiOrgs": {
    "general:HiOrg": [
      {
        "general:HiOrgId": "31",
        "general:HiOrgName": "Rettungsdienst",
        "general:HiOrgLink": "http://rd-suedpfalz.drk.de/"
      },
      {
        "general:HiOrgId": "30",
        "general:HiOrgName": "Kriminalpolizei",
        "general:HiOrgLink": "https://www.polizei.rlp.de/de/die-polizei/dienststellen/polizeipraesidium-rheinpfalz/polizeidirektion-landau/"
      },
      {
        "general:HiOrgId": "28",
        "general:HiOrgName": "Schutzpolizei",
        "general:HiOrgLink": "https://www.polizei.rlp.de/de/die-polizei/dienststellen/polizeipraesidium-rheinpfalz/polizeidirektion-landau/"
      }
    ]
  },
  "meta:geolocation": {
    "lat": 49.19209679999999,
    "lng": 8.1094755
  },
  "meta:weather": {
    "date": "2008-07-24",
    "temperature": 19,
    "temperature_min": 12.8,
    "temperature_max": 25.3,
    "precipitation": 0,
    "snowfall": null,
    "snowdepth": 0,
    "winddirection": null,
    "windspeed": 23.8,
    "peakgust": 46.4,
    "sunshine": 798,
    "pressure": null
  }
}