{
  "general:einsatzid": "2186",
  "general:title": "Unwetterschaden",
  "general:date": "2010-02-28T12:48:00+01:00",
  "general:location": "L510 Mörzheim Richtung Heuchelheim",
  "general:categorie": "Techn. Hilfeleistung",
  "general:length": "0.0",
  "general:dateFormatted": "28.02.2010 12:48",
  "general:mediaAvailable": "false",
  "general:virtualEinsatzId": "41",
  "general:changed_on": "2017-01-02T18:35:35+01:00",
  "general:AmountPA": "0",
  "general:AmountPeople": "0",
  "general:EinsatzDescription": "",
  "general:visits": "243",
  "general:vehicles": {
    "general:vehicle": [
      {
        "general:vehicleid": "51",
        "general:vehicleVersion": "0",
        "general:vehicleName": "RW (heute: RW 2)",
        "picture:Picture": {
          "picture:PicturePreviewURL": "https://www.feuerwehr-landau.de/technik/fahrzeugbilder/vorschaubilder/LD-209.jpg",
          "picture:PictureUrl": "https://www.feuerwehr-landau.de/technik/fahrzeugbilder/vollbilder/LD-209.jpg",
          "picture:PictureFormat": "quer",
          "picture:PictureDescription": "",
          "picture:BufferPreview": "true",
          "picture:BufferPicture": "true"
        },
        "general:vehicleDescription": "Rüstwagen",
        "general:vehicleChassis": "MB 1425 4x4",
        "general:vehicleBuild": "<a href=\"http://www.weschenfelder.com\" target=\"new\">Weschenfelder</a>",
        "general:vehicleMobilization": "07/05"
      },
      {
        "general:vehicleid": "56",
        "general:vehicleVersion": "0",
        "general:vehicleName": "TSF-W Mörzheim",
        "picture:Picture": {
          "picture:PicturePreviewURL": "https://www.feuerwehr-landau.de/technik/fahrzeugbilder/vorschaubilder/LD1502.jpg",
          "picture:PictureUrl": "https://www.feuerwehr-landau.de/technik/fahrzeugbilder/vollbilder/LD1502.jpg",
          "picture:PictureFormat": "quer",
          "picture:PictureDescription": "",
          "picture:BufferPreview": "true",
          "picture:BufferPicture": "true"
        },
        "general:vehicleDescription": "Tragkraftspritzenfahrzeug-Wasser",
        "general:vehicleChassis": "IVECO Daily 65C18D",
        "general:vehicleBuild": "Iveco Magirus Brandschutztechnik, jetzt: <a href=\"http://www.btg-goerlitz.biz/\" target=\"new\">Brandschutztechnik Görlitz</a>",
        "general:vehicleMobilization": "06/08"
      },
      {
        "general:vehicleid": "32",
        "general:vehicleVersion": "0",
        "general:vehicleName": "MTF Mörzheim - alt",
        "picture:Picture": {
          "picture:PicturePreviewURL": "https://www.feuerwehr-landau.de/technik/fahrzeugbilder/vorschaubilder/LD-246.JPG",
          "picture:PictureUrl": "https://www.feuerwehr-landau.de/technik/fahrzeugbilder/vollbilder/LD-246.JPG",
          "picture:PictureFormat": "quer",
          "picture:PictureDescription": "",
          "picture:BufferPreview": "true",
          "picture:BufferPicture": "true"
        },
        "general:vehicleDescription": "Mannschaftstransportfahrzeug",
        "general:vehicleChassis": "VW Bus",
        "general:vehicleBuild": "",
        "general:vehicleMobilization": "03/87"
      },
      {
        "general:vehicleid": "36",
        "general:vehicleVersion": "0",
        "general:vehicleName": "TSF Wollmesheim",
        "picture:Picture": {
          "picture:PicturePreviewURL": "https://www.feuerwehr-landau.de/technik/fahrzeugbilder/vorschaubilder/LD-270.JPG",
          "picture:PictureUrl": "https://www.feuerwehr-landau.de/technik/fahrzeugbilder/vollbilder/LD-270.JPG",
          "picture:PictureFormat": "quer",
          "picture:PictureDescription": "",
          "picture:BufferPreview": "true",
          "picture:BufferPicture": "true"
        },
        "general:vehicleDescription": "Tragkraftspritzenfahrzeug",
        "general:vehicleChassis": "VW LT",
        "general:vehicleBuild": "<a href=\"http://www.ziegler.de/index_de.php\" target=\"new\">Ziegler</a>",
        "general:vehicleMobilization": "12/87"
      }
    ]
  },
  "picture:Pictures": "",
  "general:OtherHiOrgs": "",
  "meta:geolocation": {
    "lat": 49.1671551,
    "lng": 8.0742646
  },
  "meta:weather": {
    "date": "2010-02-28",
    "temperature": 5.5,
    "temperature_min": 2.4,
    "temperature_max": 11.5,
    "precipitation": 0.8,
    "snowfall": null,
    "snowdepth": 0,
    "winddirection": null,
    "windspeed": 62.6,
    "peakgust": 163.8,
    "sunshine": 354,
    "pressure": null
  }
}