{
  "general:einsatzid": "2285",
  "general:title": "Unwetterschaden",
  "general:date": "2010-03-17T17:43:00+01:00",
  "general:location": "Spitalmühlweg",
  "general:categorie": "Techn. Hilfeleistung",
  "general:length": "1.0",
  "general:dateFormatted": "17.03.2010 17:43",
  "general:mediaAvailable": "false",
  "general:virtualEinsatzId": "139",
  "general:changed_on": "2017-01-02T18:35:35+01:00",
  "general:AmountPA": "0",
  "general:AmountPeople": "5",
  "general:EinsatzDescription": "",
  "general:visits": "506",
  "general:vehicles": {
    "general:vehicle": [
      {
        "general:vehicleid": "45",
        "general:vehicleVersion": "0",
        "general:vehicleName": "KdoW",
        "picture:Picture": {
          "picture:PicturePreviewURL": "https://www.feuerwehr-landau.de/technik/fahrzeugbilder/vorschaubilder/LD-299.jpg",
          "picture:PictureUrl": "https://www.feuerwehr-landau.de/technik/fahrzeugbilder/vollbilder/LD-299.jpg",
          "picture:PictureFormat": "quer",
          "picture:PictureDescription": "",
          "picture:BufferPreview": "true",
          "picture:BufferPicture": "true"
        },
        "general:vehicleDescription": "Kommandowagen",
        "general:vehicleChassis": "VW Passat",
        "general:vehicleBuild": "VW",
        "general:vehicleMobilization": "03/05"
      },
      {
        "general:vehicleid": "51",
        "general:vehicleVersion": "0",
        "general:vehicleName": "RW (heute: RW 2)",
        "picture:Picture": {
          "picture:PicturePreviewURL": "https://www.feuerwehr-landau.de/technik/fahrzeugbilder/vorschaubilder/LD-209.jpg",
          "picture:PictureUrl": "https://www.feuerwehr-landau.de/technik/fahrzeugbilder/vollbilder/LD-209.jpg",
          "picture:PictureFormat": "quer",
          "picture:PictureDescription": "",
          "picture:BufferPreview": "true",
          "picture:BufferPicture": "true"
        },
        "general:vehicleDescription": "Rüstwagen",
        "general:vehicleChassis": "MB 1425 4x4",
        "general:vehicleBuild": "<a href=\"http://www.weschenfelder.com\" target=\"new\">Weschenfelder</a>",
        "general:vehicleMobilization": "07/05"
      }
    ]
  },
  "picture:Pictures": "",
  "general:OtherHiOrgs": "",
  "meta:geolocation": {
    "lat": 49.1976627,
    "lng": 8.1017574
  },
  "meta:weather": {
    "date": "2010-03-17",
    "temperature": 6.8,
    "temperature_min": 2.8,
    "temperature_max": 12.6,
    "precipitation": 0,
    "snowfall": null,
    "snowdepth": 0,
    "winddirection": null,
    "windspeed": 18.4,
    "peakgust": 36.7,
    "sunshine": 228,
    "pressure": null
  }
}