{
  "general:einsatzid": "3036",
  "general:title": "Ölspur",
  "general:date": "2012-06-11T07:40:00+02:00",
  "general:location": "Stadtgebiet",
  "general:categorie": "Gefahrstoffe",
  "general:length": "1.5",
  "general:dateFormatted": "11.06.2012 07:40",
  "general:mediaAvailable": "false",
  "general:virtualEinsatzId": "136",
  "general:changed_on": "2017-01-02T18:35:35+01:00",
  "general:AmountPA": "0",
  "general:AmountPeople": "3",
  "general:EinsatzDescription": "",
  "general:visits": "277",
  "general:vehicles": {
    "general:vehicle": {
      "general:vehicleid": "1",
      "general:vehicleVersion": "0",
      "general:vehicleName": "ELW 1",
      "picture:Picture": {
        "picture:PicturePreviewURL": "https://www.feuerwehr-landau.de/technik/fahrzeugbilder/vorschaubilder/LD-207.jpg",
        "picture:PictureUrl": "https://www.feuerwehr-landau.de/technik/fahrzeugbilder/vollbilder/LD-207.jpg",
        "picture:PictureFormat": "quer",
        "picture:PictureDescription": "",
        "picture:BufferPreview": "true",
        "picture:BufferPicture": "true"
      },
      "general:vehicleDescription": "Einsatzleitwagen",
      "general:vehicleChassis": "VW LT",
      "general:vehicleBuild": "<a href=\"http://www.hensel-fahrzeugbau.de\" target=\"new\">Hensel</a>",
      "general:vehicleMobilization": "12/04"
    }
  },
  "picture:Pictures": "",
  "general:OtherHiOrgs": {
    "general:HiOrg": {
      "general:HiOrgId": "27",
      "general:HiOrgName": "Fachfirma Straßenreinigung",
      "general:HiOrgLink": "http://www.brechtel-fahrbahnreinigung.de"
    }
  },
  "meta:geolocation": {
    "lat": 49.19888599999999,
    "lng": 8.1185622
  },
  "meta:weather": {
    "date": "2012-06-11",
    "temperature": 11.8,
    "temperature_min": 9.6,
    "temperature_max": 15,
    "precipitation": 7.1,
    "snowfall": null,
    "snowdepth": null,
    "winddirection": null,
    "windspeed": 19.8,
    "peakgust": 66.2,
    "sunshine": 252,
    "pressure": null
  }
}