{
  "general:einsatzid": "3285",
  "general:title": "PKW-Brand",
  "general:date": "2013-03-20T10:18:00+01:00",
  "general:location": "Alter Messplatz",
  "general:categorie": "Brandeinsatz",
  "general:length": "0.5",
  "general:dateFormatted": "20.03.2013 10:18",
  "general:mediaAvailable": "false",
  "general:virtualEinsatzId": "83",
  "general:changed_on": "2017-01-02T18:35:35+01:00",
  "general:AmountPA": "0",
  "general:AmountPeople": "6",
  "general:EinsatzDescription": "",
  "general:visits": "434",
  "general:vehicles": {
    "general:vehicle": {
      "general:vehicleid": "60",
      "general:vehicleVersion": "1",
      "general:vehicleName": "HLF 20/16-1",
      "picture:Picture": {
        "picture:PicturePreviewURL": "https://www.feuerwehr-landau.de/technik/fahrzeugbilder/vorschaubilder/LD2016.jpg",
        "picture:PictureUrl": "https://www.feuerwehr-landau.de/technik/fahrzeugbilder/vollbilder/LD2016.jpg",
        "picture:PictureFormat": "quer",
        "picture:PictureDescription": "",
        "picture:BufferPreview": "true",
        "picture:BufferPicture": "true"
      },
      "general:vehicleDescription": "Hilfeleistungs-Löschgruppenfahrzeug",
      "general:vehicleChassis": "IVECO FF 160 E 30",
      "general:vehicleBuild": "<a href=\"http://www.ivecomagirus.net\" target=\"_new\">Iveco Magirus</a>",
      "general:vehicleMobilization": "03/09"
    }
  },
  "picture:Pictures": "",
  "general:OtherHiOrgs": "",
  "meta:geolocation": {
    "lat": 49.201332,
    "lng": 8.1095699
  },
  "meta:weather": {
    "date": "2013-03-20",
    "temperature": 1.9,
    "temperature_min": -0.7,
    "temperature_max": 5.8,
    "precipitation": 3.2,
    "snowfall": null,
    "snowdepth": 0,
    "winddirection": null,
    "windspeed": 28.8,
    "peakgust": 68.4,
    "sunshine": 132,
    "pressure": null
  }
}