{
  "general:einsatzid": "3378",
  "general:title": "Ölspur",
  "general:date": "2013-06-28T20:02:00+02:00",
  "general:location": "Brühlstraße Richtung Impflingen",
  "general:categorie": "Gefahrstoffe",
  "general:length": "1.0",
  "general:dateFormatted": "28.06.2013 20:02",
  "general:mediaAvailable": "false",
  "general:virtualEinsatzId": "173",
  "general:changed_on": "2017-01-02T18:35:35+01:00",
  "general:AmountPA": "0",
  "general:AmountPeople": "3",
  "general:EinsatzDescription": "",
  "general:visits": "227",
  "general:vehicles": {
    "general:vehicle": {
      "general:vehicleid": "1",
      "general:vehicleVersion": "0",
      "general:vehicleName": "ELW 1",
      "picture:Picture": {
        "picture:PicturePreviewURL": "https://www.feuerwehr-landau.de/technik/fahrzeugbilder/vorschaubilder/LD-207.jpg",
        "picture:PictureUrl": "https://www.feuerwehr-landau.de/technik/fahrzeugbilder/vollbilder/LD-207.jpg",
        "picture:PictureFormat": "quer",
        "picture:PictureDescription": "",
        "picture:BufferPreview": "true",
        "picture:BufferPicture": "true"
      },
      "general:vehicleDescription": "Einsatzleitwagen",
      "general:vehicleChassis": "VW LT",
      "general:vehicleBuild": "<a href=\"http://www.hensel-fahrzeugbau.de\" target=\"new\">Hensel</a>",
      "general:vehicleMobilization": "12/04"
    }
  },
  "picture:Pictures": "",
  "general:OtherHiOrgs": "",
  "meta:geolocation": {
    "lat": 49.169929,
    "lng": 8.0782302
  },
  "meta:weather": {
    "date": "2013-06-28",
    "temperature": 11.9,
    "temperature_min": 7.9,
    "temperature_max": 16.9,
    "precipitation": 3.3,
    "snowfall": null,
    "snowdepth": null,
    "winddirection": null,
    "windspeed": 17.6,
    "peakgust": 52.2,
    "sunshine": 256,
    "pressure": null
  }
}