{
  "general:einsatzid": "360",
  "general:title": "Technische Hilfeleistung",
  "general:date": "2005-05-02T18:17:00+02:00",
  "general:location": "Pestalozzistraße",
  "general:categorie": "Techn. Hilfeleistung",
  "general:length": "1.0",
  "general:dateFormatted": "02.05.2005 18:17",
  "general:mediaAvailable": "false",
  "general:virtualEinsatzId": "73",
  "general:changed_on": "2017-01-02T18:35:35+01:00",
  "general:AmountPA": "0",
  "general:AmountPeople": "4",
  "general:EinsatzDescription": "",
  "general:visits": "403",
  "general:vehicles": {
    "general:vehicle": [
      {
        "general:vehicleid": "4",
        "general:vehicleVersion": "0",
        "general:vehicleName": "TGM 23-12",
        "picture:Picture": {
          "picture:PicturePreviewURL": "https://www.feuerwehr-landau.de/technik/fahrzeugbilder/vorschaubilder/LD-243.JPG",
          "picture:PictureUrl": "https://www.feuerwehr-landau.de/technik/fahrzeugbilder/vollbilder/LD-243.JPG",
          "picture:PictureFormat": "quer",
          "picture:PictureDescription": "",
          "picture:BufferPreview": "true",
          "picture:BufferPicture": "true"
        },
        "general:vehicleDescription": "Teleskopgelenkmast",
        "general:vehicleChassis": "MAN 15.264",
        "general:vehicleBuild": "<a href=\"http://www.bronto.ch/\" target=\"new\">Bronto Skylift</a>",
        "general:vehicleMobilization": "11/98"
      },
      {
        "general:vehicleid": "45",
        "general:vehicleVersion": "0",
        "general:vehicleName": "KdoW",
        "picture:Picture": {
          "picture:PicturePreviewURL": "https://www.feuerwehr-landau.de/technik/fahrzeugbilder/vorschaubilder/LD-299.jpg",
          "picture:PictureUrl": "https://www.feuerwehr-landau.de/technik/fahrzeugbilder/vollbilder/LD-299.jpg",
          "picture:PictureFormat": "quer",
          "picture:PictureDescription": "",
          "picture:BufferPreview": "true",
          "picture:BufferPicture": "true"
        },
        "general:vehicleDescription": "Kommandowagen",
        "general:vehicleChassis": "VW Passat",
        "general:vehicleBuild": "VW",
        "general:vehicleMobilization": "03/05"
      }
    ]
  },
  "picture:Pictures": "",
  "general:OtherHiOrgs": "",
  "meta:geolocation": {
    "lat": 49.19988550000001,
    "lng": 8.108835700000002
  },
  "meta:weather": {
    "date": "2005-05-02",
    "temperature": 20.7,
    "temperature_min": 17.4,
    "temperature_max": 28,
    "precipitation": 0.1,
    "snowfall": null,
    "snowdepth": 0,
    "winddirection": null,
    "windspeed": 29.5,
    "peakgust": 68.8,
    "sunshine": 522,
    "pressure": null
  }
}