{
  "general:einsatzid": "3695",
  "general:title": "Person in Aufzug",
  "general:date": "2014-07-17T07:45:00+02:00",
  "general:location": "Thomas-Nast-Straße",
  "general:categorie": "Techn. Hilfeleistung",
  "general:length": "0.5",
  "general:dateFormatted": "17.07.2014 07:45",
  "general:mediaAvailable": "false",
  "general:virtualEinsatzId": "156",
  "general:changed_on": "2017-01-02T18:35:35+01:00",
  "general:AmountPA": "0",
  "general:AmountPeople": "7",
  "general:EinsatzDescription": "",
  "general:visits": "139",
  "general:vehicles": {
    "general:vehicle": [
      {
        "general:vehicleid": "45",
        "general:vehicleVersion": "0",
        "general:vehicleName": "KdoW",
        "picture:Picture": {
          "picture:PicturePreviewURL": "https://www.feuerwehr-landau.de/technik/fahrzeugbilder/vorschaubilder/LD-299.jpg",
          "picture:PictureUrl": "https://www.feuerwehr-landau.de/technik/fahrzeugbilder/vollbilder/LD-299.jpg",
          "picture:PictureFormat": "quer",
          "picture:PictureDescription": "",
          "picture:BufferPreview": "true",
          "picture:BufferPicture": "true"
        },
        "general:vehicleDescription": "Kommandowagen",
        "general:vehicleChassis": "VW Passat",
        "general:vehicleBuild": "VW",
        "general:vehicleMobilization": "03/05"
      },
      {
        "general:vehicleid": "60",
        "general:vehicleVersion": "1",
        "general:vehicleName": "HLF 20/16-1",
        "picture:Picture": {
          "picture:PicturePreviewURL": "https://www.feuerwehr-landau.de/technik/fahrzeugbilder/vorschaubilder/LD2016.jpg",
          "picture:PictureUrl": "https://www.feuerwehr-landau.de/technik/fahrzeugbilder/vollbilder/LD2016.jpg",
          "picture:PictureFormat": "quer",
          "picture:PictureDescription": "",
          "picture:BufferPreview": "true",
          "picture:BufferPicture": "true"
        },
        "general:vehicleDescription": "Hilfeleistungs-Löschgruppenfahrzeug",
        "general:vehicleChassis": "IVECO FF 160 E 30",
        "general:vehicleBuild": "<a href=\"http://www.ivecomagirus.net\" target=\"_new\">Iveco Magirus</a>",
        "general:vehicleMobilization": "03/09"
      }
    ]
  },
  "picture:Pictures": "",
  "general:OtherHiOrgs": "",
  "meta:geolocation": {
    "lat": 49.20792240000001,
    "lng": 8.1192777
  },
  "meta:weather": {
    "date": "2014-07-17",
    "temperature": 22.7,
    "temperature_min": 18.8,
    "temperature_max": 27.9,
    "precipitation": 0,
    "snowfall": null,
    "snowdepth": 0,
    "winddirection": null,
    "windspeed": 11.5,
    "peakgust": 32.4,
    "sunshine": 858,
    "pressure": null
  }
}