{
  "general:einsatzid": "4146",
  "general:title": "Mülleimer-Brand",
  "general:date": "2015-12-22T16:16:00+01:00",
  "general:location": "Waffenstraße",
  "general:categorie": "Brandeinsatz",
  "general:length": "0.5",
  "general:dateFormatted": "22.12.2015 16:16",
  "general:mediaAvailable": "false",
  "general:virtualEinsatzId": "300",
  "general:changed_on": "2017-01-02T18:35:35+01:00",
  "general:AmountPA": "0",
  "general:AmountPeople": "8",
  "general:EinsatzDescription": "",
  "general:visits": "22",
  "general:vehicles": {
    "general:vehicle": {
      "general:vehicleid": "60",
      "general:vehicleVersion": "1",
      "general:vehicleName": "HLF 20/16-1",
      "picture:Picture": {
        "picture:PicturePreviewURL": "https://www.feuerwehr-landau.de/technik/fahrzeugbilder/vorschaubilder/LD2016.jpg",
        "picture:PictureUrl": "https://www.feuerwehr-landau.de/technik/fahrzeugbilder/vollbilder/LD2016.jpg",
        "picture:PictureFormat": "quer",
        "picture:PictureDescription": "",
        "picture:BufferPreview": "true",
        "picture:BufferPicture": "true"
      },
      "general:vehicleDescription": "Hilfeleistungs-Löschgruppenfahrzeug",
      "general:vehicleChassis": "IVECO FF 160 E 30",
      "general:vehicleBuild": "<a href=\"http://www.ivecomagirus.net\" target=\"_new\">Iveco Magirus</a>",
      "general:vehicleMobilization": "03/09"
    }
  },
  "picture:Pictures": "",
  "general:OtherHiOrgs": "",
  "meta:geolocation": {
    "lat": 49.1975954,
    "lng": 8.1108788
  },
  "meta:weather": {
    "date": "2015-12-22",
    "temperature": 8.3,
    "temperature_min": 6.7,
    "temperature_max": 10.3,
    "precipitation": 0,
    "snowfall": null,
    "snowdepth": 0,
    "winddirection": null,
    "windspeed": 38.9,
    "peakgust": 93.6,
    "sunshine": 160,
    "pressure": null
  }
}