{
  "general:einsatzid": "442",
  "general:title": "Ölspur",
  "general:date": "2005-07-19T16:54:00+02:00",
  "general:location": "Mörzheim",
  "general:categorie": "Gefahrstoffe",
  "general:length": "2.0",
  "general:dateFormatted": "19.07.2005 16:54",
  "general:mediaAvailable": "true",
  "general:virtualEinsatzId": "153",
  "general:changed_on": "2017-01-02T18:35:35+01:00",
  "general:AmountPA": "0",
  "general:AmountPeople": "15",
  "general:EinsatzDescription": " Nicht fest montierter ?lfilter an Traktor verusachte eine ?lspur ?ber mehrere 100m durch ganz M?rzheim.  ",
  "general:visits": "454",
  "general:vehicles": {
    "general:vehicle": [
      {
        "general:vehicleid": "45",
        "general:vehicleVersion": "0",
        "general:vehicleName": "KdoW",
        "picture:Picture": {
          "picture:PicturePreviewURL": "https://www.feuerwehr-landau.de/technik/fahrzeugbilder/vorschaubilder/LD-299.jpg",
          "picture:PictureUrl": "https://www.feuerwehr-landau.de/technik/fahrzeugbilder/vollbilder/LD-299.jpg",
          "picture:PictureFormat": "quer",
          "picture:PictureDescription": "",
          "picture:BufferPreview": "true",
          "picture:BufferPicture": "true"
        },
        "general:vehicleDescription": "Kommandowagen",
        "general:vehicleChassis": "VW Passat",
        "general:vehicleBuild": "VW",
        "general:vehicleMobilization": "03/05"
      },
      {
        "general:vehicleid": "46",
        "general:vehicleVersion": "0",
        "general:vehicleName": "MZF",
        "picture:Picture": {
          "picture:PicturePreviewURL": "https://www.feuerwehr-landau.de/technik/fahrzeugbilder/vorschaubilder/LD-259.jpg",
          "picture:PictureUrl": "https://www.feuerwehr-landau.de/technik/fahrzeugbilder/vollbilder/LD-259.jpg",
          "picture:PictureFormat": "quer",
          "picture:PictureDescription": "",
          "picture:BufferPreview": "true",
          "picture:BufferPicture": "true"
        },
        "general:vehicleDescription": "Mehrzweckfahrzeug",
        "general:vehicleChassis": "MB 1425 4x4",
        "general:vehicleBuild": "<a href=\"http://www.weschenfelder.com\" target=\"new\">Weschenfelder</a>",
        "general:vehicleMobilization": "04/05"
      },
      {
        "general:vehicleid": "0",
        "general:vehicleVersion": "0",
        "general:vehicleName": "KdoW2",
        "picture:Picture": {
          "picture:PicturePreviewURL": "https://www.feuerwehr-landau.de/technik/fahrzeugbilder/vorschaubilder/LD-308.jpg",
          "picture:PictureUrl": "https://www.feuerwehr-landau.de/technik/fahrzeugbilder/vollbilder/LD-308.jpg",
          "picture:PictureFormat": "quer",
          "picture:PictureDescription": "",
          "picture:BufferPreview": "true",
          "picture:BufferPicture": "true"
        },
        "general:vehicleDescription": "Kommandowagen",
        "general:vehicleChassis": "VW Passat",
        "general:vehicleBuild": "Eigen",
        "general:vehicleMobilization": "09/88"
      },
      {
        "general:vehicleid": "31",
        "general:vehicleVersion": "0",
        "general:vehicleName": "TSF Mörzheim",
        "picture:Picture": {
          "picture:PicturePreviewURL": "https://www.feuerwehr-landau.de/technik/fahrzeugbilder/vorschaubilder/LD-311.JPG",
          "picture:PictureUrl": "https://www.feuerwehr-landau.de/technik/fahrzeugbilder/vollbilder/LD-311.JPG",
          "picture:PictureFormat": "quer",
          "picture:PictureDescription": "",
          "picture:BufferPreview": "true",
          "picture:BufferPicture": "true"
        },
        "general:vehicleDescription": "Tragkraftspritzenfahrzeug",
        "general:vehicleChassis": "VW LT",
        "general:vehicleBuild": "<a href=\"http://www.ziegler.de/index_de.php\" target=\"new\">Ziegler</a>",
        "general:vehicleMobilization": "02/86"
      },
      {
        "general:vehicleid": "32",
        "general:vehicleVersion": "0",
        "general:vehicleName": "MTF Mörzheim - alt",
        "picture:Picture": {
          "picture:PicturePreviewURL": "https://www.feuerwehr-landau.de/technik/fahrzeugbilder/vorschaubilder/LD-246.JPG",
          "picture:PictureUrl": "https://www.feuerwehr-landau.de/technik/fahrzeugbilder/vollbilder/LD-246.JPG",
          "picture:PictureFormat": "quer",
          "picture:PictureDescription": "",
          "picture:BufferPreview": "true",
          "picture:BufferPicture": "true"
        },
        "general:vehicleDescription": "Mannschaftstransportfahrzeug",
        "general:vehicleChassis": "VW Bus",
        "general:vehicleBuild": "",
        "general:vehicleMobilization": "03/87"
      }
    ]
  },
  "picture:Pictures": "",
  "general:OtherHiOrgs": "",
  "meta:geolocation": {
    "lat": 49.1682983,
    "lng": 8.073286699999999
  },
  "meta:weather": {
    "date": "2005-07-19",
    "temperature": 15.8,
    "temperature_min": 13.7,
    "temperature_max": 19.9,
    "precipitation": 1.4,
    "snowfall": null,
    "snowdepth": 0,
    "winddirection": null,
    "windspeed": 34.6,
    "peakgust": 86.4,
    "sunshine": 312,
    "pressure": null
  }
}