{
  "general:einsatzid": "4586",
  "general:title": "Fahrzeugbrand klein",
  "general:date": "2017-02-14T15:49:00+01:00",
  "general:location": "Karl-Sauer-Straße",
  "general:categorie": "Brandeinsatz",
  "general:length": "1.0",
  "general:dateFormatted": "14.02.2017 15:49",
  "general:mediaAvailable": "false",
  "general:virtualEinsatzId": "65",
  "general:changed_on": "2017-02-14T16:25:12+01:00",
  "general:AmountPA": "0",
  "general:AmountPeople": "11",
  "general:EinsatzDescription": "",
  "general:visits": "0",
  "general:vehicles": {
    "general:vehicle": {
      "general:vehicleid": "60",
      "general:vehicleVersion": "1",
      "general:vehicleName": "HLF 20/16-1",
      "picture:Picture": {
        "picture:PicturePreviewURL": "https://www.feuerwehr-landau.de/technik/fahrzeugbilder/vorschaubilder/LD2016.jpg",
        "picture:PictureUrl": "https://www.feuerwehr-landau.de/technik/fahrzeugbilder/vollbilder/LD2016.jpg",
        "picture:PictureFormat": "quer",
        "picture:PictureDescription": "",
        "picture:BufferPreview": "true",
        "picture:BufferPicture": "true"
      },
      "general:vehicleDescription": "Hilfeleistungs-Löschgruppenfahrzeug",
      "general:vehicleChassis": "IVECO FF 160 E 30",
      "general:vehicleBuild": "<a href=\"http://www.ivecomagirus.net\" target=\"_new\">Iveco Magirus</a>",
      "general:vehicleMobilization": "03/09"
    }
  },
  "picture:Pictures": "",
  "general:OtherHiOrgs": "",
  "meta:geolocation": {
    "lat": 49.1940221,
    "lng": 8.1142329
  },
  "meta:weather": {
    "date": "2017-02-14",
    "temperature": 1.9,
    "temperature_min": -1.4,
    "temperature_max": 4.8,
    "precipitation": 0,
    "snowfall": null,
    "snowdepth": null,
    "winddirection": null,
    "windspeed": 20.5,
    "peakgust": 49,
    "sunshine": 548,
    "pressure": null
  }
}