{
  "general:einsatzid": "4840",
  "general:title": "Baum über Straße",
  "general:date": "2017-10-07T17:22:00+02:00",
  "general:location": "Rohrgasse",
  "general:categorie": "Techn. Hilfeleistung",
  "general:length": "1.0",
  "general:dateFormatted": "07.10.2017 17:22",
  "general:mediaAvailable": "false",
  "general:virtualEinsatzId": "311",
  "general:changed_on": "2017-10-07T17:45:11+02:00",
  "general:AmountPA": "0",
  "general:AmountPeople": "6",
  "general:EinsatzDescription": "",
  "general:visits": "0",
  "general:vehicles": {
    "general:vehicle": {
      "general:vehicleid": "61",
      "general:vehicleVersion": "1",
      "general:vehicleName": "TSF-W Arzheim",
      "picture:Picture": {
        "picture:PicturePreviewURL": "https://www.feuerwehr-landau.de/technik/fahrzeugbilder/vorschaubilder/LD1511.jpg",
        "picture:PictureUrl": "https://www.feuerwehr-landau.de/technik/fahrzeugbilder/vollbilder/LD1511.jpg",
        "picture:PictureFormat": "quer",
        "picture:PictureDescription": "",
        "picture:BufferPreview": "true",
        "picture:BufferPicture": "true"
      },
      "general:vehicleDescription": "Tragkraftspritzenfahrzeug-Wasser",
      "general:vehicleChassis": "IVECO Daily 65C17D",
      "general:vehicleBuild": "<a href=\"http://www.adik-fahrzeugbau.de\" target=\"new\">ADIK Fahrzeugbau</a>",
      "general:vehicleMobilization": "04/11"
    }
  },
  "picture:Pictures": "",
  "general:OtherHiOrgs": "",
  "meta:geolocation": {
    "lat": 49.1937444,
    "lng": 8.0749642
  },
  "meta:weather": {
    "date": "2017-10-07",
    "temperature": 6.9,
    "temperature_min": 5,
    "temperature_max": 8.9,
    "precipitation": 1.3,
    "snowfall": null,
    "snowdepth": 0,
    "winddirection": null,
    "windspeed": 38.9,
    "peakgust": 83.2,
    "sunshine": 6,
    "pressure": null
  }
}