{
  "general:einsatzid": "5701",
  "general:title": "Gebäudebrand",
  "general:date": "2018-11-24T14:59:00+01:00",
  "general:location": "Max-Slevogt-Straße",
  "general:categorie": "Brandeinsatz",
  "general:length": "2.5",
  "general:dateFormatted": "24.11.2018 14:59",
  "general:mediaAvailable": "true",
  "general:virtualEinsatzId": "742",
  "picture:Picture": {
    "picture:PicturePreviewURL": "https://www.feuerwehr-landau.de/einsatz/einsatzbilder/vorschaubilder/1811/5701-4.jpeg",
    "picture:PictureUrl": "https://www.feuerwehr-landau.de/einsatz/einsatzbilder/vollbilder/1811/5701-4.jpeg",
    "picture:PictureFormat": "quer",
    "picture:PictureDescription": "",
    "picture:BufferPreview": "true",
    "picture:BufferPicture": "false"
  },
  "general:changed_on": "2018-11-25T08:26:02+01:00",
  "general:AmountPA": "6",
  "general:AmountPeople": "44",
  "general:EinsatzDescription": "<p><strong>Landau. Am heutigen Samstag wurde die Freiwillige Feuerwehr Landau innerhalb kurzer Zeit zu zwei Geb&auml;udebr&auml;nden alarmiert. Im Landauer Stadtteil Horst war es bei einem Gebrauchtwagenh&auml;ndler zu einem Brand mehrerer Fahrzeuge sowie einem Anbau einer Halle gekommen. Gleichzeitig musste im Stadtteil Godramstein der Brand im ersten Obergeschoss eines Wohnhauses gel&ouml;scht werden.&nbsp;</strong></p>\n<p>Um 14:18 Uhr erreichte die Alarmierung mit dem Stichwort &bdquo;PKW-Brand&ldquo; die Einsatzkr&auml;fte der Freiwilligen Feuerwehr Landau. &bdquo;Beim Eintreffen der Einsatzkr&auml;fte in der Taubensuhlstra&szlig;e wurde ein ausgedehnter Brand festgestellt. Der Brand eines Kraftfahrzeuges hatte bereits auf die Halle &uuml;bergegriffen. Die Rauchs&auml;ule war weit sichtbar&ldquo;, so Stadtfeuerwehrinspekteur Dirk Hargesheimer. Ein weiteres &Uuml;bergreifen auf angrenzende Geb&auml;ude konnte jedoch verhindert werden. Noch w&auml;hrend der L&ouml;scharbeiten alarmierte die integrierte Leitstelle Landau die Einsatzkr&auml;fte zu einem Geb&auml;udebrand nach Godramstein: &bdquo;Sofort wurden die Einsatzkr&auml;fte der Ausr&uuml;ckegemeinschaft Arzheim-Godramstein sowie weitere Fahrzeuge aus der Feuerwache Landau zur Einsatzstelle entsandt. Zus&auml;tzlich wurde die Freiwillige Feuerwehr Annweiler mit einem Hubrettungsfahrzeug alarmiert&ldquo;, so Hargesheimer weiter. Beide Br&auml;nde konnten schnell unter Kontrolle gebracht werden. Verletzt wurde niemand. Insgesamt waren 75 Einsatzkr&auml;fte der Feuerwehr sowie weitere Einsatzkr&auml;fte von Polizei, Rettungsdienst und THW OV Landau im Einsatz. (bhi)</p>",
  "general:visits": "0",
  "general:vehicles": {
    "general:vehicle": [
      {
        "general:vehicleid": "1",
        "general:vehicleVersion": "0",
        "general:vehicleName": "ELW 1",
        "picture:Picture": {
          "picture:PicturePreviewURL": "https://www.feuerwehr-landau.de/technik/fahrzeugbilder/vorschaubilder/LD-207.jpg",
          "picture:PictureUrl": "https://www.feuerwehr-landau.de/technik/fahrzeugbilder/vollbilder/LD-207.jpg",
          "picture:PictureFormat": "quer",
          "picture:PictureDescription": "",
          "picture:BufferPreview": "true",
          "picture:BufferPicture": "true"
        },
        "general:vehicleDescription": "Einsatzleitwagen",
        "general:vehicleChassis": "VW LT",
        "general:vehicleBuild": "<a href=\"http://www.hensel-fahrzeugbau.de\" target=\"new\">Hensel</a>",
        "general:vehicleMobilization": "12/04"
      },
      {
        "general:vehicleid": "78",
        "general:vehicleVersion": "4",
        "general:vehicleName": "stellv. SFI",
        "picture:Picture": {
          "picture:PicturePreviewURL": "https://www.feuerwehr-landau.de/kam/default.jpg",
          "picture:PictureUrl": "https://www.feuerwehr-landau.de/kam/default.jpg",
          "picture:PictureFormat": "hoch",
          "picture:PictureDescription": "Bild folgt",
          "picture:BufferPreview": "true",
          "picture:BufferPicture": "true"
        },
        "general:vehicleDescription": "",
        "general:vehicleChassis": "",
        "general:vehicleBuild": "",
        "general:vehicleMobilization": ""
      },
      {
        "general:vehicleid": "70",
        "general:vehicleVersion": "1",
        "general:vehicleName": "LF-KatS",
        "picture:Picture": {
          "picture:PicturePreviewURL": "https://www.feuerwehr-landau.de/technik/fahrzeugbilder/vorschaubilder/LD8045.jpg",
          "picture:PictureUrl": "https://www.feuerwehr-landau.de/technik/fahrzeugbilder/vollbilder/LD8045.jpg",
          "picture:PictureFormat": "quer",
          "picture:PictureDescription": "",
          "picture:BufferPreview": "true",
          "picture:BufferPicture": "true"
        },
        "general:vehicleDescription": "Löschgruppenfahrzeug Katastrophenschutz",
        "general:vehicleChassis": "MAN TGM 13.250 4x4 BL FW",
        "general:vehicleBuild": "<a href=\"http://www.lentner-gmbh.de\" target=\"new\">Josef Lentner GmbH</a>",
        "general:vehicleMobilization": "09/12"
      },
      {
        "general:vehicleid": "57",
        "general:vehicleVersion": "2",
        "general:vehicleName": "TSF-W Godramstein",
        "picture:Picture": {
          "picture:PicturePreviewURL": "https://www.feuerwehr-landau.de/technik/fahrzeugbilder/vorschaubilder/LD1503.jpg",
          "picture:PictureUrl": "https://www.feuerwehr-landau.de/technik/fahrzeugbilder/vollbilder/LD1503.jpg",
          "picture:PictureFormat": "quer",
          "picture:PictureDescription": "",
          "picture:BufferPreview": "true",
          "picture:BufferPicture": "true"
        },
        "general:vehicleDescription": "Tragkraftspritzenfahrzeug-Wasser",
        "general:vehicleChassis": "IVECO Daily 65C18D",
        "general:vehicleBuild": "Iveco Magirus Brandschutztechnik, jetzt: <a href=\"http://www.btg-goerlitz.biz/\" target=\"new\">Brandschutztechnik Görlitz</a>",
        "general:vehicleMobilization": "06/08"
      },
      {
        "general:vehicleid": "63",
        "general:vehicleVersion": "1",
        "general:vehicleName": "MTF Godramstein",
        "picture:Picture": {
          "picture:PicturePreviewURL": "https://www.feuerwehr-landau.de/technik/fahrzeugbilder/vorschaubilder/LD1505.jpg",
          "picture:PictureUrl": "https://www.feuerwehr-landau.de/technik/fahrzeugbilder/vollbilder/LD1505.jpg",
          "picture:PictureFormat": "quer",
          "picture:PictureDescription": "",
          "picture:BufferPreview": "true",
          "picture:BufferPicture": "true"
        },
        "general:vehicleDescription": "Mannschaftstransportfahrzeug",
        "general:vehicleChassis": "VW T5",
        "general:vehicleBuild": "<a href=\"http://www.auto-zotz.de\" target=\"new\">Auto Zotz</a>; Weschenfelder",
        "general:vehicleMobilization": "02/08"
      },
      {
        "general:vehicleid": "61",
        "general:vehicleVersion": "1",
        "general:vehicleName": "TSF-W Arzheim",
        "picture:Picture": {
          "picture:PicturePreviewURL": "https://www.feuerwehr-landau.de/technik/fahrzeugbilder/vorschaubilder/LD1511.jpg",
          "picture:PictureUrl": "https://www.feuerwehr-landau.de/technik/fahrzeugbilder/vollbilder/LD1511.jpg",
          "picture:PictureFormat": "quer",
          "picture:PictureDescription": "",
          "picture:BufferPreview": "true",
          "picture:BufferPicture": "true"
        },
        "general:vehicleDescription": "Tragkraftspritzenfahrzeug-Wasser",
        "general:vehicleChassis": "IVECO Daily 65C17D",
        "general:vehicleBuild": "<a href=\"http://www.adik-fahrzeugbau.de\" target=\"new\">ADIK Fahrzeugbau</a>",
        "general:vehicleMobilization": "04/11"
      },
      {
        "general:vehicleid": "24",
        "general:vehicleVersion": "1",
        "general:vehicleName": "SFI",
        "picture:Picture": {
          "picture:PicturePreviewURL": "https://www.feuerwehr-landau.de/kam/default.jpg",
          "picture:PictureUrl": "https://www.feuerwehr-landau.de/kam/default.jpg",
          "picture:PictureFormat": "hoch",
          "picture:PictureDescription": "Bild folgt",
          "picture:BufferPreview": "true",
          "picture:BufferPicture": "true"
        },
        "general:vehicleDescription": "",
        "general:vehicleChassis": "",
        "general:vehicleBuild": "",
        "general:vehicleMobilization": ""
      },
      {
        "general:vehicleid": "2",
        "general:vehicleVersion": "1",
        "general:vehicleName": "HLF 20/16-2",
        "picture:Picture": {
          "picture:PicturePreviewURL": "https://www.feuerwehr-landau.de/technik/fahrzeugbilder/vorschaubilder/LD-204.jpg",
          "picture:PictureUrl": "https://www.feuerwehr-landau.de/technik/fahrzeugbilder/vollbilder/LD-204.jpg",
          "picture:PictureFormat": "quer",
          "picture:PictureDescription": "",
          "picture:BufferPreview": "true",
          "picture:BufferPicture": "true"
        },
        "general:vehicleDescription": "Hilfeleistungs-Löschgruppenfahrzeug",
        "general:vehicleChassis": "IVECO 135E24W",
        "general:vehicleBuild": "<a href=\"http://www.iveco-magirus.de/\" target=\"new\">Iveco-Magirus</a>",
        "general:vehicleMobilization": "03/02"
      },
      {
        "general:vehicleid": "46",
        "general:vehicleVersion": "1",
        "general:vehicleName": "MZF",
        "picture:Picture": {
          "picture:PicturePreviewURL": "https://www.feuerwehr-landau.de/technik/fahrzeugbilder/vorschaubilder/LD-259.jpg",
          "picture:PictureUrl": "https://www.feuerwehr-landau.de/technik/fahrzeugbilder/vollbilder/LD-259.jpg",
          "picture:PictureFormat": "quer",
          "picture:PictureDescription": "",
          "picture:BufferPreview": "true",
          "picture:BufferPicture": "true"
        },
        "general:vehicleDescription": "Mehrzweckfahrzeug",
        "general:vehicleChassis": "MB 1425 4x4",
        "general:vehicleBuild": "<a href=\"http://www.weschenfelder.com\" target=\"new\">Weschenfelder</a>",
        "general:vehicleMobilization": "04/05"
      },
      {
        "general:vehicleid": "65",
        "general:vehicleVersion": "0",
        "general:vehicleName": "MTF 1",
        "picture:Picture": {
          "picture:PicturePreviewURL": "https://www.feuerwehr-landau.de/technik/fahrzeugbilder/vorschaubilder/LD1513.jpg",
          "picture:PictureUrl": "https://www.feuerwehr-landau.de/technik/fahrzeugbilder/vollbilder/LD1513.jpg",
          "picture:PictureFormat": "quer",
          "picture:PictureDescription": "",
          "picture:BufferPreview": "true",
          "picture:BufferPicture": "true"
        },
        "general:vehicleDescription": "Mannschaftstransportfahrzeug",
        "general:vehicleChassis": "Ford Transit",
        "general:vehicleBuild": "<a href=\"http://www.compoint-fahrzeugbau.de\" target=\"new\">Compoint</a>",
        "general:vehicleMobilization": "06/11"
      }
    ]
  },
  "picture:Pictures": {
    "picture:Picture": [
      {
        "picture:PicturePreviewURL": "https://www.feuerwehr-landau.de/einsatz/einsatzbilder/vorschaubilder/1811/5701-4.jpeg",
        "picture:PictureUrl": "https://www.feuerwehr-landau.de/einsatz/einsatzbilder/vollbilder/1811/5701-4.jpeg",
        "picture:PictureFormat": "quer",
        "picture:PictureDescription": "",
        "picture:BufferPreview": "true",
        "picture:BufferPicture": "false"
      },
      {
        "picture:PicturePreviewURL": "https://www.feuerwehr-landau.de/einsatz/einsatzbilder/vorschaubilder/1811/5701-5.jpeg",
        "picture:PictureUrl": "https://www.feuerwehr-landau.de/einsatz/einsatzbilder/vollbilder/1811/5701-5.jpeg",
        "picture:PictureFormat": "quer",
        "picture:PictureDescription": "",
        "picture:BufferPreview": "true",
        "picture:BufferPicture": "false"
      }
    ]
  },
  "general:OtherHiOrgs": {
    "general:HiOrg": [
      {
        "general:HiOrgId": "31",
        "general:HiOrgName": "Rettungsdienst",
        "general:HiOrgLink": "http://rd-suedpfalz.drk.de/"
      },
      {
        "general:HiOrgId": "28",
        "general:HiOrgName": "Schutzpolizei",
        "general:HiOrgLink": "https://www.polizei.rlp.de/de/die-polizei/dienststellen/polizeipraesidium-rheinpfalz/polizeidirektion-landau/"
      },
      {
        "general:HiOrgId": "47",
        "general:HiOrgName": "THW OV Landau",
        "general:HiOrgLink": "http://www.thw-landau.de"
      },
      {
        "general:HiOrgId": "48",
        "general:HiOrgName": "FF Annweiler",
        "general:HiOrgLink": "http://www.feuerwehr-annweiler.de/"
      }
    ]
  },
  "meta:geolocation": {
    "lat": 49.2133472,
    "lng": 8.0866251
  },
  "meta:weather": {
    "date": "2018-11-24",
    "temperature": 3.4,
    "temperature_min": 0.2,
    "temperature_max": 6.6,
    "precipitation": 1.1,
    "snowfall": null,
    "snowdepth": 0,
    "winddirection": 192,
    "windspeed": 23.9,
    "peakgust": 47,
    "sunshine": 5,
    "pressure": 1013
  }
}