{
  "general:einsatzid": "6371",
  "general:title": "Gefahrstoffaustritt kleinerer Art",
  "general:date": "2020-04-11T15:55:00+02:00",
  "general:location": "Hainbachstraße",
  "general:categorie": "Gefahrstoffe",
  "general:length": "0.5",
  "general:dateFormatted": "11.04.2020 15:55",
  "general:mediaAvailable": "false",
  "general:virtualEinsatzId": "120",
  "general:changed_on": "2020-04-11T15:59:30+02:00",
  "general:AmountPA": "0",
  "general:AmountPeople": "3",
  "general:EinsatzDescription": "",
  "general:visits": "0",
  "general:vehicles": {
    "general:vehicle": {
      "general:vehicleid": "15",
      "general:vehicleVersion": "2",
      "general:vehicleName": "KLAF",
      "picture:Picture": {
        "picture:PicturePreviewURL": "https://www.feuerwehr-landau.de/technik/fahrzeugbilder/vorschaubilder/LD-263.jpg",
        "picture:PictureUrl": "https://www.feuerwehr-landau.de/technik/fahrzeugbilder/vollbilder/LD-263.jpg",
        "picture:PictureFormat": "quer",
        "picture:PictureDescription": "",
        "picture:BufferPreview": "true",
        "picture:BufferPicture": "true"
      },
      "general:vehicleDescription": "Kleinalarmfahrzeug",
      "general:vehicleChassis": "MB Sprinter",
      "general:vehicleBuild": "Eigen",
      "general:vehicleMobilization": "03/12"
    }
  },
  "picture:Pictures": "",
  "general:OtherHiOrgs": {
    "general:HiOrg": {
      "general:HiOrgId": "28",
      "general:HiOrgName": "Schutzpolizei",
      "general:HiOrgLink": "https://www.polizei.rlp.de/de/die-polizei/dienststellen/polizeipraesidium-rheinpfalz/polizeidirektion-landau/"
    }
  },
  "meta:geolocation": {
    "lat": 49.2076803,
    "lng": 8.124348
  },
  "meta:weather": {
    "date": "2020-04-11",
    "temperature": 14.8,
    "temperature_min": 9.8,
    "temperature_max": 20.1,
    "precipitation": 0,
    "snowfall": null,
    "snowdepth": 0,
    "winddirection": 60,
    "windspeed": 15,
    "peakgust": 31,
    "sunshine": 755,
    "pressure": 1022.9
  }
}